dogu-server
setup.cfg
setup.py
dogu/__init__.py
dogu/data_frame_io.py
dogu/http2_error_codes.py
dogu/http2_exception.py
dogu/logger.py
dogu/server.py
dogu/util.py
dogu.egg-info/PKG-INFO
dogu.egg-info/SOURCES.txt
dogu.egg-info/dependency_links.txt
dogu.egg-info/requires.txt
dogu.egg-info/top_level.txt
dogu/connection/__init__.py
dogu/connection/http1.py
dogu/connection/http2.py
dogu/frame/__init__.py
dogu/frame/data_frame.py
dogu/frame/goaway_frame.py
dogu/frame/header_frame.py
dogu/frame/ping_frame.py
dogu/frame/priority_frame.py
dogu/frame/push_promise_frame.py
dogu/frame/rst_frame.py
dogu/frame/setting_frame.py
dogu/frame/window_update.py
dogu/stream/__init__.py
dogu/stream/http1.py
dogu/stream/http2.py